nrpcalc/__init__.py
nrpcalc/nrpcalc.py
nrpcalc/base/__init__.py
nrpcalc/base/berno.py
nrpcalc/base/finder.py
nrpcalc/base/hgraph.py
nrpcalc/base/kmerSetArray.py
nrpcalc/base/kmerSetDB.py
nrpcalc/base/maker.py
nrpcalc/base/makerchecks.py
nrpcalc/base/projector.py
nrpcalc/base/recovery.py
nrpcalc/base/synthesis.py
nrpcalc/base/utils.py
nrpcalc/base/vercov.py
nrpcalc-1.7.5.dist-info/LICENSE
nrpcalc-1.7.5.dist-info/METADATA
nrpcalc-1.7.5.dist-info/WHEEL
nrpcalc-1.7.5.dist-info/top_level.txt
nrpcalc-1.7.5.dist-info/RECORD
