Metadata-Version: 2.1
Name: nrpcalc
Version: 1.7.5
Summary: Non-Repetitive Parts Calculator - Automated design and discovery of non-repetitive genetic parts for engineering stable genetic systems
Home-page: https://github.com/ayaanhossain/nrpcalc
Author: Ayaan Hossain and Howard Salis
Author-email: auh57@psu.edu, salis@psu.edu
Project-URL: Bug Reports, https://github.com/ayaanhossain/nrpcalc/issues
Project-URL: Source, https://github.com/ayaanhossain/nrpcalc/tree/master/nrpcalc
Keywords: synthetic computational biology genetic parts calculator non-repetitive design discovery algorithm stable systems nrp repeats vertex cover path finding
Classifier: Development Status :: 4 - Beta
Classifier: Intended Audience :: Science/Research
Classifier: Topic :: Scientific/Engineering
Classifier: Topic :: Scientific/Engineering :: Bio-Informatics
Classifier: Topic :: Scientific/Engineering :: Chemistry
Classifier: License :: OSI Approved :: MIT License
Classifier: Programming Language :: Python :: 3.6
Classifier: Programming Language :: Python :: 3.7
Classifier: Programming Language :: Python :: 3.8
Classifier: Programming Language :: Python :: 3.9
Requires-Python: >=3.6, <4
License-File: LICENSE
Requires-Dist: numpy >=1.19.0
Requires-Dist: biopython >=1.77
Requires-Dist: sharedb >=1.1.4
Requires-Dist: scipy >=1.5.1
Requires-Dist: networkx >=2.4
Requires-Dist: jupyter >=1.0.0
Requires-Dist: scikit-learn >=0.23.1
Requires-Dist: seaborn >=0.10.1
Requires-Dist: statsmodels >=0.11.0
Requires-Dist: ViennaRNA >=2.4.18a1
